pds/peppi/VERSION.txt
pds/peppi/__init__.py
pds/peppi/client.py
pds/peppi/context_base.py
pds/peppi/contexts.py
pds/peppi/mcp_server.py
pds/peppi/products.py
pds/peppi/query_builder.py
pds/peppi/result_set.py
pds/peppi/orex/__init__.py
pds/peppi/orex/products.py
pds/peppi/orex/query_builder.py
pds_peppi-0.8.0.dist-info/licenses/LICENSE.md
pds_peppi-0.8.0.dist-info/licenses/NOTICE.txt
pds_peppi-0.8.0.dist-info/METADATA
pds_peppi-0.8.0.dist-info/WHEEL
pds_peppi-0.8.0.dist-info/entry_points.txt
pds_peppi-0.8.0.dist-info/top_level.txt
pds_peppi-0.8.0.dist-info/zip-safe
pds_peppi-0.8.0.dist-info/RECORD
