Metadata-Version: 2.4
Name: pds.peppi
Version: 0.8.0
Summary: Get Planetary Data from the Planetary Data System (PDS)
Home-page: https://github.com/NASA-PDS/peppi
Download-URL: https://github.com/NASA-PDS/peppi/releases/
Author: PDS
Author-email: pds_operator@jpl.nasa.gov
License: apache-2.0
Keywords: pds,planetary data,api
Classifier: Programming Language :: Python :: 3
Classifier: Programming Language :: Python :: 3.13
Classifier: Operating System :: OS Independent
Requires-Python: >=3.13
License-File: LICENSE.md
License-File: NOTICE.txt
Requires-Dist: pds.api-client~=1.7.0
Requires-Dist: pandas~=2.2.3
Requires-Dist: RapidFuzz~=3.14.0
Requires-Dist: fastmcp~=2.12.0
Provides-Extra: dev
Requires-Dist: flake8~=7.3.0; extra == "dev"
Requires-Dist: flake8-bugbear~=24.12.12; extra == "dev"
Requires-Dist: flake8-docstrings~=1.7.0; extra == "dev"
Requires-Dist: pep8-naming<0.15.0,>=0.13.3; extra == "dev"
Requires-Dist: mypy~=1.14.1; extra == "dev"
Requires-Dist: pydocstyle~=6.3.0; extra == "dev"
Requires-Dist: coverage~=7.3.0; extra == "dev"
Requires-Dist: pytest<8.4,>=7.4; extra == "dev"
Requires-Dist: pytest-cov~=4.1.0; extra == "dev"
Requires-Dist: pytest-watch~=4.2.0; extra == "dev"
Requires-Dist: pytest-xdist~=3.3.1; extra == "dev"
Requires-Dist: pre-commit~=3.3.3; extra == "dev"
Requires-Dist: sphinx~=8.2.3; extra == "dev"
Requires-Dist: sphinx-rtd-theme~=3.0.2; extra == "dev"
Requires-Dist: tox~=4.11.0; extra == "dev"
Requires-Dist: types-setuptools<74.1.1,>=68.1.0; extra == "dev"
Dynamic: download-url
Dynamic: license-file
